ci/__init__.py
ci/constants.py
ci/rebuild_updated_recipes.py
pythonforandroid/__init__.py
pythonforandroid/androidndk.py
pythonforandroid/archs.py
pythonforandroid/bdistapk.py
pythonforandroid/bootstrap.py
pythonforandroid/build.py
pythonforandroid/checkdependencies.py
pythonforandroid/distribution.py
pythonforandroid/entrypoints.py
pythonforandroid/graph.py
pythonforandroid/logger.py
pythonforandroid/patching.py
pythonforandroid/prerequisites.py
pythonforandroid/pythonpackage.py
pythonforandroid/recipe.py
pythonforandroid/recommendations.py
pythonforandroid/toolchain.py
pythonforandroid/util.py
pythonforandroid/bootstraps/__init__.py
pythonforandroid/bootstraps/common/build/ant.properties
pythonforandroid/bootstraps/common/build/build.py
pythonforandroid/bootstraps/common/build/gradlew
pythonforandroid/bootstraps/common/build/gradlew.bat
pythonforandroid/bootstraps/common/build/whitelist.txt
pythonforandroid/bootstraps/common/build/gradle/wrapper/gradle-wrapper.jar
pythonforandroid/bootstraps/common/build/gradle/wrapper/gradle-wrapper.properties
pythonforandroid/bootstraps/common/build/jni/Android.mk
pythonforandroid/bootstraps/common/build/jni/application/Android.mk
pythonforandroid/bootstraps/common/build/jni/application/src/Android.mk
pythonforandroid/bootstraps/common/build/jni/application/src/start.c
pythonforandroid/bootstraps/common/build/src/main/java/org/kamranzafar/jtar/Octal.java
pythonforandroid/bootstraps/common/build/src/main/java/org/kamranzafar/jtar/TarConstants.java
pythonforandroid/bootstraps/common/build/src/main/java/org/kamranzafar/jtar/TarEntry.java
pythonforandroid/bootstraps/common/build/src/main/java/org/kamranzafar/jtar/TarHeader.java
pythonforandroid/bootstraps/common/build/src/main/java/org/kamranzafar/jtar/TarInputStream.java
pythonforandroid/bootstraps/common/build/src/main/java/org/kamranzafar/jtar/TarOutputStream.java
pythonforandroid/bootstraps/common/build/src/main/java/org/kamranzafar/jtar/TarUtils.java
python_for_android-2024.1.21.dist-info/LICENSE
python_for_android-2024.1.21.dist-info/METADATA
python_for_android-2024.1.21.dist-info/WHEEL
python_for_android-2024.1.21.dist-info/entry_points.txt
python_for_android-2024.1.21.dist-info/top_level.txt
python_for_android-2024.1.21.dist-info/RECORD
