Metadata-Version: 2.1
Name: python-for-android
Version: 2024.1.21
Summary: A development tool that packages Python apps into binaries that can run on Android devices.
Home-page: https://github.com/kivy/python-for-android
Author: Kivy Team and other contributors
Author-email: kivy-dev@googlegroups.com
License: MIT
Project-URL: Documentation, https://python-for-android.readthedocs.io
Project-URL: Source, https://github.com/kivy/python-for-android
Project-URL: Bug Reports, https://github.com/kivy/python-for-android/issues
Classifier: Development Status :: 5 - Production/Stable
Classifier: Intended Audience :: Developers
Classifier: License :: OSI Approved :: MIT License
Classifier: Operating System :: Microsoft :: Windows
Classifier: Operating System :: OS Independent
Classifier: Operating System :: POSIX :: Linux
Classifier: Operating System :: MacOS :: MacOS X
Classifier: Operating System :: Android
Classifier: Programming Language :: C
Classifier: Programming Language :: Python :: 3
Classifier: Programming Language :: Python :: 3.7
Classifier: Programming Language :: Python :: 3.8
Classifier: Programming Language :: Python :: 3.9
Classifier: Programming Language :: Python :: 3.10
Classifier: Programming Language :: Python :: 3.11
Classifier: Topic :: Software Development
Classifier: Topic :: Utilities
Requires-Python: >=3.7.0
License-File: LICENSE
Requires-Dist: appdirs
Requires-Dist: colorama>=0.3.3
Requires-Dist: jinja2
Requires-Dist: sh<2.0,>=1.10; sys_platform != "win32"
Requires-Dist: build
Requires-Dist: toml
Requires-Dist: packaging
Requires-Dist: setuptools
